Problem01.py
Problem02.py
Problem41.py
gep_python_coding_challenge-0.0.5.dist-info/LICENSE
gep_python_coding_challenge-0.0.5.dist-info/METADATA
gep_python_coding_challenge-0.0.5.dist-info/WHEEL
gep_python_coding_challenge-0.0.5.dist-info/top_level.txt
gep_python_coding_challenge-0.0.5.dist-info/RECORD
