Metadata-Version: 2.1
Name: gep-python-coding-challenge
Version: 0.0.5
Summary: This package contains the beginner level assignments of the GEP Python Coding Challenge.
Home-page: https://github.com/Joyce-NL/gep-python-coding-challenge
Author: JcS
Author-email: joyce@hey.com
License: MIT
Keywords: Euler,Project Euler
Platform: UNKNOWN
Classifier: Development Status :: 3 - Alpha
Classifier: Intended Audience :: Developers
Classifier: License :: OSI Approved :: MIT License
Classifier: Operating System :: OS Independent
Classifier: Programming Language :: Python
Classifier: Programming Language :: Python :: 3
Classifier: Topic :: Other/Nonlisted Topic
Requires-Python: >=3.0
